console_log/__init__.py
console_log/consoleLog.py
shoe-0.1.9.data/scripts/shoe
shoelib/__init__.py
shoelib/shoeBond.py
shoelib/shoeCfgXml.py
shoelib/shoeCmnd.py
shoelib/shoeDev.py
shoelib/shoeEventParser.py
shoelib/shoeMsg.py
shoelib/shoeMsgXml.py
shoelib/shoeOp.py
shoelib/shoeRoot.py
shoelib/shoeSvc.py
shoelib/shoeVer.py
shoelib/test_shoe/__init__.py
shoelib/test_shoe/testActDev.py
shoelib/test_shoe/testActSvc.py
shoelib/test_shoe/testAiosSvcDev.py
shoelib/test_shoe/testGroupCtrlSvc.py
shoelib/test_shoe/testMediaSrvDev.py
shoelib/test_shoe/testRendererDev.py
shoelib/test_shoe/testRootDev.py
shoelib/test_shoe/testShoeCmnd.py
shoelib/test_shoe/testShoeDev.py
shoelib/test_shoe/testShoeEvent.py
shoelib/test_shoe/testShoeHttp.py
shoelib/test_shoe/testShoeSvc.py
shoelib/test_shoe/testShoeXml.py
shoelib/test_shoe/testZoneCtrlSvc.py
shoelib/test_shoe/toeJam.py
shoelib/test_shoe/ut_shoeBond.py
shoelib/test_shoe/ut_shoeCfgXml.py
shoelib/test_shoe/ut_shoeCmnd.py
shoelib/test_shoe/ut_shoeDev.py
shoelib/test_shoe/ut_shoeEventParser.py
shoelib/test_shoe/ut_shoeMsg.py
shoelib/test_shoe/ut_shoeMsgXml.py
shoelib/test_shoe/ut_shoeOp.py
shoelib/test_shoe/ut_shoeRoot.py
shoelib/test_shoe/ut_shoeSvc.py
shoe-0.1.9.dist-info/LICENSE
shoe-0.1.9.dist-info/METADATA
shoe-0.1.9.dist-info/WHEEL
shoe-0.1.9.dist-info/top_level.txt
shoe-0.1.9.dist-info/RECORD
