Metadata-Version: 2.1
Name: shoe
Version: 0.1.9
Summary: Configuration and control for HEOS speakers
Home-page: https://github.com/mkarasoff/shoe
Author: Michael Karasoff
Author-email: mike@karatronics.com
License: UNKNOWN
Platform: UNKNOWN
Classifier: Programming Language :: Python :: 3
Classifier: Natural Language :: English
Classifier: License :: OSI Approved :: GNU General Public License v3 (GPLv3)
Classifier: Operating System :: OS Independent
Requires-Python: >=3.6
